dovalens/__init__.py
dovalens/__main__.py
dovalens/cli.py
dovalens/core.py
dovalens/report.py
dovalens/utils.py
dovalens-1.0.5.dist-info/licenses/LICENSE
dovalens-1.0.5.dist-info/METADATA
dovalens-1.0.5.dist-info/WHEEL
dovalens-1.0.5.dist-info/entry_points.txt
dovalens-1.0.5.dist-info/top_level.txt
dovalens-1.0.5.dist-info/RECORD
