Metadata-Version: 2.4
Name: dovalens
Version: 1.0.5
Summary: Automated dataset analyzer and HTML report generator
Author: Pietro Ferreri
License: MIT License
Project-URL: Homepage, https://pypi.org/project/dovalens/
Project-URL: Source, https://github.com/Dova-Digit/DovaLens
Project-URL: Issues, https://github.com/Dova-Digit/DovaLens/issues
Project-URL: Changelog, https://github.com/Dova-Digit/DovaLens/blob/main/CHANGELOG.md
Requires-Python: >=3.9
License-File: LICENSE
Requires-Dist: pandas
Requires-Dist: numpy
Requires-Dist: scikit-learn
Requires-Dist: scipy
Dynamic: license-file
Dynamic: requires-python
